practical_astronomy/__init__.py
practical_astronomy/pa_binary.py
practical_astronomy/pa_binary_data.py
practical_astronomy/pa_comet.py
practical_astronomy/pa_comet_data.py
practical_astronomy/pa_coordinate.py
practical_astronomy/pa_datetime.py
practical_astronomy/pa_eclipses.py
practical_astronomy/pa_macro.py
practical_astronomy/pa_moon.py
practical_astronomy/pa_planet.py
practical_astronomy/pa_planet_data.py
practical_astronomy/pa_sun.py
practical_astronomy/pa_util.py
practical_astronomy-1.0.2.dist-info/METADATA
practical_astronomy-1.0.2.dist-info/WHEEL
practical_astronomy-1.0.2.dist-info/licenses/LICENSE
practical_astronomy-1.0.2.dist-info/RECORD
