Metadata-Version: 2.3
Name: practical-astronomy
Version: 1.0.2
Summary: Algorithms from Practical Astronomy, implemented in Python
Project-URL: Homepage, https://github.com/jfcarr/practical-astronomy-python
Project-URL: Issues, https://github.com/jfcarr/practical-astronomy-python/issues
Project-URL: Documentation, https://jfcarr.github.io/practical-astronomy-python
Author-email: Jim Carr <jfcarr@gmail.com>
License-File: LICENSE
Classifier: License :: OSI Approved :: MIT License
Classifier: Operating System :: OS Independent
Classifier: Programming Language :: Python :: 3
Requires-Python: >=3.8
